{"nodes": [{"id": "backend_api_clients_ejscreen_py", "label": "ejscreen.py", "file_type": "code", "source_file": "backend/api_clients/ejscreen.py", "source_location": "L1"}, {"id": "ejscreen_query_ejscreen", "label": "query_ejscreen()", "file_type": "code", "source_file": "backend/api_clients/ejscreen.py", "source_location": "L13"}, {"id": "ejscreen_rationale_14", "label": "Query Census ACS 5-year estimates for environmental justice demographic indicato", "file_type": "rationale", "source_file": "backend/api_clients/ejscreen.py", "source_location": "L14"}], "edges": [{"source": "backend_api_clients_ejscreen_py", "target": "logging", "relation": "imports", "confidence": "EXTRACTED", "source_file": "backend/api_clients/ejscreen.py", "source_location": "L1", "weight": 1.0}, {"source": "backend_api_clients_ejscreen_py", "target": "httpx", "relation": "imports", "confidence": "EXTRACTED", "source_file": "backend/api_clients/ejscreen.py", "source_location": "L3", "weight": 1.0}, {"source": "backend_api_clients_ejscreen_py", "target": "ejscreen_query_ejscreen", "relation": "contains", "confidence": "EXTRACTED", "source_file": "backend/api_clients/ejscreen.py", "source_location": "L13", "weight": 1.0}, {"source": "ejscreen_rationale_14", "target": "ejscreen_query_ejscreen", "relation": "rationale_for", "confidence": "EXTRACTED", "source_file": "backend/api_clients/ejscreen.py", "source_location": "L14", "weight": 1.0}], "raw_calls": [{"caller_nid": "ejscreen_query_ejscreen", "callee": "info", "source_file": "backend/api_clients/ejscreen.py", "source_location": "L16"}, {"caller_nid": "ejscreen_query_ejscreen", "callee": "get", "source_file": "backend/api_clients/ejscreen.py", "source_location": "L17"}, {"caller_nid": "ejscreen_query_ejscreen", "callee": "info", "source_file": "backend/api_clients/ejscreen.py", "source_location": "L24"}, {"caller_nid": "ejscreen_query_ejscreen", "callee": "raise_for_status", "source_file": "backend/api_clients/ejscreen.py", "source_location": "L25"}, {"caller_nid": "ejscreen_query_ejscreen", "callee": "get", "source_file": "backend/api_clients/ejscreen.py", "source_location": "L28"}, {"caller_nid": "ejscreen_query_ejscreen", "callee": "get", "source_file": "backend/api_clients/ejscreen.py", "source_location": "L28"}, {"caller_nid": "ejscreen_query_ejscreen", "callee": "get", "source_file": "backend/api_clients/ejscreen.py", "source_location": "L28"}, {"caller_nid": "ejscreen_query_ejscreen", "callee": "json", "source_file": "backend/api_clients/ejscreen.py", "source_location": "L28"}, {"caller_nid": "ejscreen_query_ejscreen", "callee": "ValueError", "source_file": "backend/api_clients/ejscreen.py", "source_location": "L34"}, {"caller_nid": "ejscreen_query_ejscreen", "callee": "info", "source_file": "backend/api_clients/ejscreen.py", "source_location": "L39"}, {"caller_nid": "ejscreen_query_ejscreen", "callee": "info", "source_file": "backend/api_clients/ejscreen.py", "source_location": "L50"}, {"caller_nid": "ejscreen_query_ejscreen", "callee": "get", "source_file": "backend/api_clients/ejscreen.py", "source_location": "L51"}, {"caller_nid": "ejscreen_query_ejscreen", "callee": "join", "source_file": "backend/api_clients/ejscreen.py", "source_location": "L52"}, {"caller_nid": "ejscreen_query_ejscreen", "callee": "info", "source_file": "backend/api_clients/ejscreen.py", "source_location": "L56"}, {"caller_nid": "ejscreen_query_ejscreen", "callee": "raise_for_status", "source_file": "backend/api_clients/ejscreen.py", "source_location": "L57"}, {"caller_nid": "ejscreen_query_ejscreen", "callee": "json", "source_file": "backend/api_clients/ejscreen.py", "source_location": "L59"}, {"caller_nid": "ejscreen_query_ejscreen", "callee": "dict", "source_file": "backend/api_clients/ejscreen.py", "source_location": "L60"}, {"caller_nid": "ejscreen_query_ejscreen", "callee": "zip", "source_file": "backend/api_clients/ejscreen.py", "source_location": "L60"}, {"caller_nid": "ejscreen_query_ejscreen", "callee": "int", "source_file": "backend/api_clients/ejscreen.py", "source_location": "L62"}, {"caller_nid": "ejscreen_query_ejscreen", "callee": "get", "source_file": "backend/api_clients/ejscreen.py", "source_location": "L62"}, {"caller_nid": "ejscreen_query_ejscreen", "callee": "int", "source_file": "backend/api_clients/ejscreen.py", "source_location": "L63"}, {"caller_nid": "ejscreen_query_ejscreen", "callee": "get", "source_file": "backend/api_clients/ejscreen.py", "source_location": "L63"}, {"caller_nid": "ejscreen_query_ejscreen", "callee": "int", "source_file": "backend/api_clients/ejscreen.py", "source_location": "L64"}, {"caller_nid": "ejscreen_query_ejscreen", "callee": "get", "source_file": "backend/api_clients/ejscreen.py", "source_location": "L64"}, {"caller_nid": "ejscreen_query_ejscreen", "callee": "int", "source_file": "backend/api_clients/ejscreen.py", "source_location": "L65"}, {"caller_nid": "ejscreen_query_ejscreen", "callee": "get", "source_file": "backend/api_clients/ejscreen.py", "source_location": "L65"}, {"caller_nid": "ejscreen_query_ejscreen", "callee": "round", "source_file": "backend/api_clients/ejscreen.py", "source_location": "L67"}, {"caller_nid": "ejscreen_query_ejscreen", "callee": "round", "source_file": "backend/api_clients/ejscreen.py", "source_location": "L68"}, {"caller_nid": "ejscreen_query_ejscreen", "callee": "info", "source_file": "backend/api_clients/ejscreen.py", "source_location": "L83"}]}